tree_types/TreeTypes.py
tree_types/__init__.py
tree_types/enums/PrintMode.py
tree_types/enums/__init__.py
tree_types-0.2.2.dist-info/licenses/LICENSE
tree_types-0.2.2.dist-info/METADATA
tree_types-0.2.2.dist-info/WHEEL
tree_types-0.2.2.dist-info/top_level.txt
tree_types-0.2.2.dist-info/RECORD
