Metadata-Version: 2.4
Name: tree_types
Version: 0.2.2
Summary: A Class that computes the types of elements in a Object
Author-email: Mayron Moura Soares Junior <mayronjunior5@gmail.com>
License-Expression: MIT
Project-URL: Homepage, https://github.com/mayronjr/pip-tree-types
Classifier: Programming Language :: Python :: 3.9
Classifier: Programming Language :: Python :: 3.10
Classifier: Programming Language :: Python :: 3.11
Classifier: Programming Language :: Python :: 3.12
Classifier: Programming Language :: Python :: 3.13
Classifier: Operating System :: OS Independent
Requires-Python: >=3.9
License-File: LICENSE
Dynamic: license-file
